spacetime/__init__.py
spacetime/__main__.py
spacetime/client/IApplication.py
spacetime/client/IFrame.py
spacetime/client/__init__.py
spacetime/client/declarations.py
spacetime/client/frame.py
spacetime/client/store.py
spacetime/common/__init__.py
spacetime/common/converter.py
spacetime/common/crawler_generator.py
spacetime/common/instrument.py
spacetime/common/javahttpadapter.py
spacetime/common/modes.py
spacetime/common/util.py
spacetime/common/wire_formats.py
spacetime/server/__init__.py
spacetime/server/store.py
spacetime/server/store_server_flask.py
spacetime/server/store_server_tornado.py
spacetime-0.2.1.dist-info/DESCRIPTION.rst
spacetime-0.2.1.dist-info/METADATA
spacetime-0.2.1.dist-info/RECORD
spacetime-0.2.1.dist-info/WHEEL
spacetime-0.2.1.dist-info/metadata.json
spacetime-0.2.1.dist-info/top_level.txt
