Metadata-Version: 2.0
Name: spacetime
Version: 0.2.1
Summary: Spacetime Application Framework
Home-page: https://github.com/Mondego/spacetime
Author: Rohan Achar
Author-email: ra.rohan@gmail.com
License: MIT
Keywords: spacetime,distributed frameworks,distributed simulation frameworks
Platform: UNKNOWN
Classifier: Development Status :: 3 - Alpha
Classifier: Intended Audience :: Developers
Classifier: Intended Audience :: Education
Classifier: Intended Audience :: Science/Research
Classifier: Topic :: Software Development :: Libraries
Classifier: Topic :: Software Development :: Libraries :: Application Frameworks
Classifier: License :: OSI Approved :: MIT License
Classifier: Programming Language :: Python :: 2
Classifier: Programming Language :: Python :: 2.6
Classifier: Programming Language :: Python :: 2.7
Requires-Dist: dill
Requires-Dist: lxml
Requires-Dist: pcc
Requires-Dist: requests
Requires-Dist: tornado
Provides-Extra: dev
Provides-Extra: flask
Requires-Dist: flask; extra == 'flask'
Provides-Extra: test
